pyblst-0.3.14.dist-info/METADATA
pyblst-0.3.14.dist-info/WHEEL
pyblst-0.3.14.dist-info/licenses/LICENSE.txt
pyblst/__init__.py
pyblst/pyblst.cpython-312-aarch64-linux-gnu.so
pyblst-0.3.14.dist-info/RECORD
